cert_host_scraper/__init__.py
cert_host_scraper/cli.py
cert_host_scraper/scraper.py
cert_host_scraper/utils.py
cert_host_scraper-0.10.5.dist-info/METADATA
cert_host_scraper-0.10.5.dist-info/WHEEL
cert_host_scraper-0.10.5.dist-info/entry_points.txt
cert_host_scraper-0.10.5.dist-info/licenses/LICENSE
cert_host_scraper-0.10.5.dist-info/RECORD
