Metadata-Version: 2.4
Name: cert-host-scraper
Version: 0.10.5
Summary: Query the certificate transparency log from crt.sh by a given a keyword and returns the status code of the matched results. Optionally, filtering the results by status code.
Project-URL: homepage, https://github.com/inverse/cert-host-scraper
Project-URL: repository, https://github.com/inverse/cert-host-scraper
Author-email: Malachi Soord <inverse.chi@gmail.com>
License-Expression: MIT
License-File: LICENSE
Requires-Python: <4,>=3.10
Requires-Dist: click<9,>=8.1.8
Requires-Dist: requests<3,>=2.27.1
Requires-Dist: rich<15,>=11
Requires-Dist: single-source<0.5,>=0.4.0
Requires-Dist: tenacity<10,>=9.0.0
